Metadata-Version: 2.1
Name: math-package-08
Version: 0.1
Summary: Mathematical functions
Home-page: UNKNOWN
Author: Naheen Bijapure
Author-email: naheenbijapure094@gmail.com
License: UNKNOWN
Platform: UNKNOWN
